{
    "products": [
        {
            "id":1,
            "producttitle": "กำไลข้อมือ1",
            "description": "กำไลเงิน",
            "price": 500
        },
        {
            "id":2,
            "producttitle": "กำไลข้อมือ2",
            "description": "กำไลทอง",
            "price": 800
        },
        {
            "id":3,
            "producttitle": "กำไลข้อมือ3",
            "description": "กำไลเพชร",
            "price": 1000
        },
        {
            "id":4,
            "producttitle": "กำไลข้อมือ4",
            "description": "กำไลทองแดง",
            "price": 300
        }
    ]
}